pyvboxmanage/PyVBoxManage.py
pyvboxmanage/__init__.py
pyvboxmanage/cli/__init__.py
pyvboxmanage/cli/click.py
pyvboxmanage/cli/entrypoints.py
pyvboxmanage/exceptions/PyVBoxManageException.py
pyvboxmanage/exceptions/__init__.py
pyvboxmanage/utils/__init__.py
pyvboxmanage/utils/bin_file.py
pyvboxmanage/utils/binfile.py
pyvboxmanage/utils/config.py
pyvboxmanage/utils/dict_merge.py
pyvboxmanage/utils/exec_command.py
pyvboxmanage/utils/logger.py
pyvboxmanage/utils/merge.py
pyvboxmanage-0.4.2.dist-info/LICENSE.txt
pyvboxmanage-0.4.2.dist-info/METADATA
pyvboxmanage-0.4.2.dist-info/WHEEL
pyvboxmanage-0.4.2.dist-info/entry_points.txt
pyvboxmanage-0.4.2.dist-info/top_level.txt
pyvboxmanage-0.4.2.dist-info/zip-safe
pyvboxmanage-0.4.2.dist-info/RECORD
