Metadata-Version: 2.1
Name: pyvboxmanage
Version: 0.4.2
Summary: Wrapper tool around VBoxManage that facilitates the orchestration of VBoxManage commands from a simple YAML configuration file that matches the input opts/args for VBoxManage.
Home-page: https://pyvboxmanage.readthedocs.io
Author: Nicholas de Jong
Author-email: me@nicholasdejong.com
License: BSD2
Keywords: virtuabox,vbox,vboxmanage,devops
Platform: UNKNOWN
Classifier: Environment :: Console
Classifier: Intended Audience :: Developers
Classifier: Intended Audience :: Information Technology
Classifier: Programming Language :: Python :: 3.5
Classifier: Programming Language :: Python :: 3.6
Classifier: Programming Language :: Python :: 3.7
Classifier: Programming Language :: Python :: 3.8
Classifier: Programming Language :: Python :: 3.9
Classifier: License :: OSI Approved :: BSD License
Requires-Python: >=3.5.0,<4.0.0
License-File: LICENSE.txt
Requires-Dist: click (>=7.1.0)
Requires-Dist: pyyaml
